simple_sqla_timer.py
simple_sqla_timer-0.1.0.dist-info/LICENSE
simple_sqla_timer-0.1.0.dist-info/WHEEL
simple_sqla_timer-0.1.0.dist-info/METADATA
simple_sqla_timer-0.1.0.dist-info/RECORD
