Metadata-Version: 2.1
Name: simple-sqla-timer
Version: 0.1.0
Summary: A simple way of logging how long it takes for SQLAlchemy queries to run.
Home-page: https://github.com/Barbora-Data-Science/simple-sqla-timer
License: Apache-2.0
Author: Saulius Beinorius
Author-email: saulius.beinorius@gmail.com
Maintainer: Saulius Beinorius
Maintainer-email: saulius.beinorius@gmail.com
Requires-Python: >=3.7,<4.0
Classifier: License :: OSI Approved :: Apache Software License
Classifier: Programming Language :: Python :: 3
Classifier: Programming Language :: Python :: 3.7
Classifier: Programming Language :: Python :: 3.8
Classifier: Programming Language :: Python :: 3.9
Classifier: Topic :: Software Development :: Libraries :: Python Modules
Requires-Dist: SQLAlchemy (>=1.3.19,<2.0.0)
Project-URL: Repository, https://github.com/Barbora-Data-Science/simple-sqla-timer
